.gitignore
.hgtags
LICENSE
MANIFEST.in
README.md
setup.py
DElauncher4Kodi/__init__.py
DElauncher4Kodi/__main__.py
DElauncher4Kodi/__version__.py
DElauncher4Kodi/key_redirection.py
DElauncher4Kodi/volume_adjustment.py
DElauncher4Kodi/xbmcclient.py
DElauncher4Kodi.egg-info/PKG-INFO
DElauncher4Kodi.egg-info/SOURCES.txt
DElauncher4Kodi.egg-info/dependency_links.txt
DElauncher4Kodi.egg-info/requires.txt
DElauncher4Kodi.egg-info/top_level.txt
data/99-DElauncher4Kodi-uinput-group-access.rules
data/DElauncher4Kodi.conf
data/org.DElauncher4Kodi.desktop