Metadata-Version: 2.1
Name: DElauncher4Kodi
Version: 1.2.3
Summary: Kodi launcher grabbing media keys and adjusting system volume.
Home-page: https://github.com/chrisjbillington/DElauncher4Kodi/
Author: Chris Billington
Author-email: chrisjbillington@gmail.com
License: GPL2
Platform: UNKNOWN
License-File: LICENSE
